pacifica_cli-0.5.2-py3.8-nspkg.pth
pacifica/cli/__init__.py
pacifica/cli/__main__.py
pacifica/cli/_version.py
pacifica/cli/config_schema.json
pacifica/cli/configure.py
pacifica/cli/methods.py
pacifica/cli/query.py
pacifica/cli/upload.py
pacifica/cli/utils.py
pacifica_cli-0.5.2.dist-info/LICENSE
pacifica_cli-0.5.2.dist-info/METADATA
pacifica_cli-0.5.2.dist-info/WHEEL
pacifica_cli-0.5.2.dist-info/entry_points.txt
pacifica_cli-0.5.2.dist-info/namespace_packages.txt
pacifica_cli-0.5.2.dist-info/top_level.txt
pacifica_cli-0.5.2.dist-info/RECORD
