Metadata-Version: 2.1
Name: pacifica-cli
Version: 0.5.2
Summary: Pacifica CLI Tool
Home-page: https://github.com/pacifica/pacifica-cli/
Author: David Brown
Author-email: david.brown@pnnl.gov
License: UNKNOWN
Platform: UNKNOWN
Requires-Dist: jsonschema
Requires-Dist: pacifica-downloader (>=0.4.1)
Requires-Dist: pacifica-namespace
Requires-Dist: pacifica-uploader (>=0.3.1)
Requires-Dist: pager
